conftrak/__init__.py
conftrak/_version.py
conftrak/exceptions.py
conftrak/ignition.py
conftrak/startup.py
conftrak/client/__init__.py
conftrak/client/commands.py
conftrak/client/conf.py
conftrak/client/utils.py
conftrak/schemas/configuration.json
conftrak/server/__init__.py
conftrak/server/conf.py
conftrak/server/engine.py
conftrak/server/utils.py
conftrak/test/__init__.py
conftrak/test/conftest.py
conftrak/test/test_client_commands.py
conftrak/test/test_client_utils.py
conftrak/test/test_server.py
conftrak-0.0.9.dist-info/LICENSE
conftrak-0.0.9.dist-info/METADATA
conftrak-0.0.9.dist-info/WHEEL
conftrak-0.0.9.dist-info/entry_points.txt
conftrak-0.0.9.dist-info/top_level.txt
conftrak-0.0.9.dist-info/RECORD
