Metadata-Version: 2.1
Name: conftrak
Version: 0.0.9
Summary: Beamline and General Configurations Tracker and Storage
Home-page: https://github.com/hhslepicka/conftrak.git
License: BSD 3-Clause
Classifier: License :: OSI Approved :: BSD License
Classifier: Development Status :: 3 - Alpha
Classifier: Programming Language :: Python :: 3
Requires-Python: >=3.6
License-File: LICENSE
Requires-Dist: doct
Requires-Dist: jsonschema
Requires-Dist: pymongo
Requires-Dist: pyyaml
Requires-Dist: requests
Requires-Dist: tornado
Requires-Dist: ujson
